<metadata>
  <idinfo>
    <citation>
      <citeinfo>
        <title>RECREATION_BikeRacks</title>
        <geoform>vector digital data</geoform>
      </citeinfo>
    </citation>
    <descript>
      <abstract>Bicycle parking data for public land in the city has been created through three methods: site surveys, detection through aerial imagery, and installation tracking. The data does not include bicycle parking on private property and excludes some racks that do not meet the city’s standards for rack design.</abstract>
      <purpose>Bicycle parking data for public land in the city.</purpose>
    </descript>
    <spdom>
      <bounding>
        <westbc>-71.155239</westbc>
        <eastbc>-71.070606</eastbc>
        <northbc>42.400562</northbc>
        <southbc>42.355303</southbc>
      </bounding>
    </spdom>
    <accconst>None</accconst>
    <useconst>None</useconst>
    <datacred>City of Cambridge Community Development Department (CDD)</datacred>
    <native> Version 6.2 (Build 9200) ; Esri ArcGIS 10.4.1.5713</native>
  </idinfo>
  <spdoinfo>
    <direct>Vector</direct>
    <ptvctinf>
      <sdtsterm>
        <sdtstype>Entity point</sdtstype>
        <ptvctcnt>2456</ptvctcnt>
      </sdtsterm>
    </ptvctinf>
  </spdoinfo>
  <spref>
    <horizsys>
      <planar>
        <mapproj>
          <mapprojn>NAD 1983 StatePlane Massachusetts Mainland FIPS 2001 Feet</mapprojn>
          <lambertc>
            <stdparll>41.71666666666667</stdparll>
            <stdparll>42.68333333333333</stdparll>
            <longcm>-71.5</longcm>
            <latprjo>41.0</latprjo>
            <feast>656166.6666666665</feast>
            <fnorth>2460625.0</fnorth>
          </lambertc>
        </mapproj>
        <planci>
          <plance>coordinate pair</plance>
          <coordrep>
            <absres>0.00032808333333333333</absres>
            <ordres>0.00032808333333333333</ordres>
          </coordrep>
          <plandu>foot_us</plandu>
        </planci>
      </planar>
      <geodetic>
        <horizdn>D North American 1983</horizdn>
        <ellips>GRS 1980</ellips>
        <semiaxis>6378137.0</semiaxis>
        <denflat>298.257222101</denflat>
      </geodetic>
    </horizsys>
  </spref>
  <eainfo>
    <detailed>
      <enttyp>
        <enttypl>RECREATION_BikeRacks</enttypl>
      </enttyp>
      <attr>
        <attrlabl>Shape</attrlabl>
        <attrdef>Feature geometry.</attrdef>
        <attrdefs>Esri</attrdefs>
        <attrdomv>
          <udom>Coordinates defining the features.</udom>
        </attrdomv>
      </attr>
      <attr>
        <attrlabl>Racks</attrlabl>
        <attrdef>Number of racks at location.</attrdef>
      </attr>
      <attr>
        <attrlabl>Location</attrlabl>
        <attrdef>Description of location (address, landmark, etc.).</attrdef>
      </attr>
      <attr>
        <attrlabl>OBJECTID</attrlabl>
        <attrdef>Internal feature number.</attrdef>
        <attrdefs>Esri</attrdefs>
        <attrdomv>
          <udom>Sequential unique whole numbers that are automatically generated.</udom>
        </attrdomv>
      </attr>
      <attr>
        <attrlabl>CAPACITY</attrlabl>
        <attrdef>Number of bicycle parking spaces at location</attrdef>
      </attr>
      <attr>
        <attrlabl>Owner</attrlabl>
        <attrdef>Owner of the property on which the rack(s) was installed.</attrdef>
      </attr>
      <attr>
        <attrlabl>RequestNumber</attrlabl>
      </attr>
      <attr>
        <attrlabl>Cross_St</attrlabl>
      </attr>
      <attr>
        <attrlabl>BizLocator</attrlabl>
      </attr>
      <attr>
        <attrlabl>Latitude</attrlabl>
      </attr>
      <attr>
        <attrlabl>Longitude</attrlabl>
      </attr>
      <attr>
        <attrlabl>RackType</attrlabl>
      </attr>
      <attr>
        <attrlabl>InstallTyp</attrlabl>
      </attr>
      <attr>
        <attrlabl>Traff_Mgmt</attrlabl>
      </attr>
      <attr>
        <attrlabl>Meter_Num</attrlabl>
      </attr>
      <attr>
        <attrlabl>DateInstall</attrlabl>
      </attr>
      <attr>
        <attrlabl>SurveyDate</attrlabl>
      </attr>
      <attr>
        <attrlabl>Ref_Number</attrlabl>
      </attr>
      <attr>
        <attrlabl>Ped_Volume</attrlabl>
      </attr>
      <attr>
        <attrlabl>SurveyNote</attrlabl>
      </attr>
      <attr>
        <attrlabl>SQ_VOs_ADA</attrlabl>
      </attr>
      <attr>
        <attrlabl>CornerDist</attrlabl>
      </attr>
      <attr>
        <attrlabl>BusLoadADA</attrlabl>
      </attr>
      <attr>
        <attrlabl>VaultSewer</attrlabl>
      </attr>
      <attr>
        <attrlabl>ImpedeEntr</attrlabl>
      </attr>
      <attr>
        <attrlabl>OutSitPoss</attrlabl>
      </attr>
      <attr>
        <attrlabl>CurbWall</attrlabl>
      </attr>
      <attr>
        <attrlabl>PedWalkway</attrlabl>
      </attr>
      <attr>
        <attrlabl>Orientation</attrlabl>
      </attr>
      <attr>
        <attrlabl>MoveObst</attrlabl>
      </attr>
      <attr>
        <attrlabl>Round</attrlabl>
      </attr>
      <attr>
        <attrlabl>Status</attrlabl>
      </attr>
      <attr>
        <attrlabl>CurbRegs</attrlabl>
      </attr>
      <attr>
        <attrlabl>Spacing</attrlabl>
      </attr>
      <attr>
        <attrlabl>MeterSpace</attrlabl>
      </attr>
      <attr>
        <attrlabl>Needs_TPT</attrlabl>
      </attr>
      <attr>
        <attrlabl>Confirmed</attrlabl>
      </attr>
      <attr>
        <attrlabl>StatusNotes</attrlabl>
      </attr>
      <attr>
        <attrlabl>SurfaceTyp</attrlabl>
      </attr>
      <attr>
        <attrlabl>InstallPKG</attrlabl>
      </attr>
      <attr>
        <attrlabl>Priority</attrlabl>
      </attr>
      <attr>
        <attrlabl>Photo_Num</attrlabl>
      </attr>
      <attr>
        <attrlabl>Full_Addr</attrlabl>
      </attr>
      <attr>
        <attrlabl>DigSafeNum</attrlabl>
      </attr>
      <attr>
        <attrlabl>SpecialCat</attrlabl>
      </attr>
      <attr>
        <attrlabl>SurveyBy</attrlabl>
      </attr>
      <attr>
        <attrlabl>DesignEx</attrlabl>
      </attr>
      <attr>
        <attrlabl>GlobalID</attrlabl>
      </attr>
    </detailed>
  </eainfo>
  <metainfo>
    <metd>20170123</metd>
    <metstdn>FGDC Content Standard for Digital Geospatial Metadata</metstdn>
    <metstdv>FGDC-STD-001-1998</metstdv>
    <mettc>local time</mettc>
  </metainfo>
</metadata>